dojo_ds/__init__.py
dojo_ds/_eda_functions_plotly.py
dojo_ds/cli.py
dojo_ds/data_enrichment.py
dojo_ds/datasets.py
dojo_ds/deploy.py
dojo_ds/eda.py
dojo_ds/evaluate.py
dojo_ds/fileinfo.py
dojo_ds/imports.py
dojo_ds/insights.py
dojo_ds/matplotlib_style.py
dojo_ds/nlp.py
dojo_ds/time_series.py
dojo_ds/utils.py
dojo_ds-1.1.15.dist-info/AUTHORS.rst
dojo_ds-1.1.15.dist-info/LICENSE
dojo_ds-1.1.15.dist-info/METADATA
dojo_ds-1.1.15.dist-info/WHEEL
dojo_ds-1.1.15.dist-info/entry_points.txt
dojo_ds-1.1.15.dist-info/top_level.txt
dojo_ds-1.1.15.dist-info/RECORD
