Metadata-Version: 2.1
Name: dojo_ds
Version: 1.1.15
Summary: Code from Coding Dojo's Online Part-Time Data Science boot camp
Home-page: https://github.com/coding-dojo-data-science/dojo_ds
Author: James Irving
Author-email: jirving@codingdojo.com
License: GNU General Public License v3
Keywords: dojo_ds
Classifier: Development Status :: 2 - Pre-Alpha
Classifier: Intended Audience :: Developers
Classifier: License :: OSI Approved :: GNU General Public License v3 (GPLv3)
Classifier: Natural Language :: English
Classifier: Programming Language :: Python :: 3
Classifier: Programming Language :: Python :: 3.8
Classifier: Programming Language :: Python :: 3.9
Classifier: Programming Language :: Python :: 3.10
Classifier: Programming Language :: Python :: 3.11
Classifier: Programming Language :: Python :: 3.12
Requires-Python: >=3.6
License-File: LICENSE
License-File: AUTHORS.rst
